LICENSE
README.md
pyproject.toml
requirements.txt
tests/test_example_complex_uqmodels.py
tests/test_pre_processing.py
tests/test_tutorial_uqmodels.py
tests/test_uqestimators.py
tests/test_uqmodels.py
uqmodels/UQModel.py
uqmodels/__init__.py
uqmodels/check.py
uqmodels/custom_UQModel.py
uqmodels/processing.py
uqmodels/utils.py
uqmodels.egg-info/PKG-INFO
uqmodels.egg-info/SOURCES.txt
uqmodels.egg-info/dependency_links.txt
uqmodels.egg-info/requires.txt
uqmodels.egg-info/top_level.txt
uqmodels/data_generation/Gen_basic_times_series.py
uqmodels/data_generation/Gen_multivariate_normal_data.py
uqmodels/data_generation/Gen_two_dimension_uncertainty_data.py
uqmodels/evaluation/__init__.py
uqmodels/evaluation/base_metrics.py
uqmodels/evaluation/evaluation.py
uqmodels/evaluation/metrics.py
uqmodels/modelization/UQEstimator.py
uqmodels/modelization/__init__.py
uqmodels/modelization/DL_estimator/Lstm_WS_ED.py
uqmodels/modelization/DL_estimator/__init__.py
uqmodels/modelization/DL_estimator/baseline_models.py
uqmodels/modelization/DL_estimator/data_embedding.py
uqmodels/modelization/DL_estimator/data_generator.py
uqmodels/modelization/DL_estimator/loss.py
uqmodels/modelization/DL_estimator/lstm_ed.py
uqmodels/modelization/DL_estimator/metalayers.py
uqmodels/modelization/DL_estimator/neural_network_UQ.py
uqmodels/modelization/DL_estimator/transformer_ed.py
uqmodels/modelization/DL_estimator/utils.py
uqmodels/modelization/ML_estimator/__init__.py
uqmodels/modelization/ML_estimator/baseline.py
uqmodels/modelization/ML_estimator/random_forest_UQ.py
uqmodels/postprocessing/UQKPI_Processor.py
uqmodels/postprocessing/UQ_processing.py
uqmodels/postprocessing/__init__.py
uqmodels/postprocessing/anomaly_processing.py
uqmodels/postprocessing/custom_UQKPI_Processor.py
uqmodels/preprocessing/Custom_Preprocessor.py
uqmodels/preprocessing/Preprocessor.py
uqmodels/preprocessing/__init__.py
uqmodels/preprocessing/data_loader.py
uqmodels/preprocessing/features_processing.py
uqmodels/preprocessing/preprocessing.py
uqmodels/preprocessing/structure.py
uqmodels/preprocessing/tsfresh_utils.py
uqmodels/preprocessing/utils.py
