Metadata-Version: 2.4
Name: uqmodels
Version: 1.1.1
Summary: Predictive Uncertainty Quantification Models
Author: Kevin Pasini
Author-email: kevin.pasini@irt-systemx.fr
License-Expression: Apache-2.0
Project-URL: Homepage, https://irt-systemx.github.io/uqmodels
Project-URL: Documentation, https://irt-systemx.github.io/uqmodels
Project-URL: Repository, https://github.com/IRT-SystemX/uqmodels
Requires-Python: <3.13,>=3.10
License-File: LICENSE
Requires-Dist: joblib==1.4.2
Requires-Dist: jsonpickle==3.0.2
Requires-Dist: matplotlib==3.7.3
Requires-Dist: numpy==1.26.4
Requires-Dist: pandas==2.2.2
Requires-Dist: scikit_learn==1.7.0
Requires-Dist: scipy==1.14.0
Requires-Dist: tensorflow[and-cuda]==2.18.1
Requires-Dist: tsfresh==0.21.1
Requires-Dist: xgboost==3.1.2
Requires-Dist: statsmodels==0.14.4
Dynamic: license-file
